AUTHORS.rst
LICENSE
MANIFEST.in
README.rst
setup.py
django_sendsms.egg-info/PKG-INFO
django_sendsms.egg-info/SOURCES.txt
django_sendsms.egg-info/dependency_links.txt
django_sendsms.egg-info/not-zip-safe
django_sendsms.egg-info/requires.txt
django_sendsms.egg-info/top_level.txt
sendsms/__init__.py
sendsms/api.py
sendsms/exceptions.py
sendsms/message.py
sendsms/signals.py
sendsms/utils.py
sendsms/backends/__init__.py
sendsms/backends/base.py
sendsms/backends/console.py
sendsms/backends/dummy.py
sendsms/backends/esendex.py
sendsms/backends/filebased.py
sendsms/backends/locmem.py
sendsms/backends/smsglobal.py
sendsms/backends/smspubli.py
sendsms/backends/smssluzbacz.py
sendsms/backends/twiliorest.py